repo_cloner/__init__.py
repo_cloner/cloner.py
repo_cloner/yml_reader.py
repo_cloner-1.0.0.dist-info/LICENSE
repo_cloner-1.0.0.dist-info/METADATA
repo_cloner-1.0.0.dist-info/WHEEL
repo_cloner-1.0.0.dist-info/entry_points.txt
repo_cloner-1.0.0.dist-info/top_level.txt
repo_cloner-1.0.0.dist-info/RECORD
