Metadata-Version: 2.1
Name: repo-cloner
Version: 1.0.0
Summary: Python utility for cloning repositories
Home-page: https://github.com/danpeczek/repo-cloner
Author: Daniel Peczek
Author-email: danpeczek@gmail.com
License: UNKNOWN
Project-URL: Bug Tracker, https://github.com/danpeczek/repo-cloner/issues
Platform: UNKNOWN
Classifier: Environment :: Console
Classifier: Intended Audience :: Developers
Classifier: Operating System :: POSIX
Classifier: Programming Language :: Python
Classifier: Topic :: Communications :: Email
Classifier: Topic :: Software Development :: Bug Tracking
Requires-Python: >=3.6
License-File: LICENSE
Requires-Dist: pyyaml
